acrylic/Color.py
acrylic/Converters.py
acrylic/Defaults.py
acrylic/Palette.py
acrylic/Schemes.py
acrylic/Validators.py
acrylic/__init__.py
acrylic/color_names.py
acrylic-0.3.0.dist-info/LICENSE.txt
acrylic-0.3.0.dist-info/METADATA
acrylic-0.3.0.dist-info/WHEEL
acrylic-0.3.0.dist-info/top_level.txt
acrylic-0.3.0.dist-info/RECORD
