Metadata-Version: 2.1
Name: acrylic
Version: 0.3.0
Summary: A simple and intuitive library to work with colors in python
Home-page: https://github.com/prdx23/acrylic
Author: Arsh
Author-email: hi@prdx.me
License: UNKNOWN
Project-URL: Source, https://github.com/prdx23/acrylic
Project-URL: Tracker, https://github.com/prdx23/acrylic/issues
Keywords: color colors scheme palette rgb hsv hsl ryb hex colour colours
Platform: UNKNOWN
Classifier: Programming Language :: Python :: 3
Classifier: Programming Language :: Python :: 3.6
Classifier: Programming Language :: Python :: 3.7
Classifier: Programming Language :: Python :: 3.8
Classifier: Programming Language :: Python :: 3.9
Classifier: License :: OSI Approved :: MIT License
Classifier: Operating System :: OS Independent
Classifier: Development Status :: 4 - Beta
Classifier: Intended Audience :: Developers
Requires-Python: >=3.6
